hackernews_scraper
