Metadata-Version: 1.0
Name: hackernews-scraper
Version: 1.0.2
Summary: Python library for retrieving comments and stories from HackerNews
Home-page: https://github.com/NiGhTTraX/hackernews-scraper
Author: UNKNOWN
Author-email: UNKNOWN
License: MIT
Platform: any
